lightgbm/VERSION.txt
lightgbm/__init__.py
lightgbm/basic.py
lightgbm/callback.py
lightgbm/compat.py
lightgbm/dask.py
lightgbm/engine.py
lightgbm/lib/lib_lightgbm.so
lightgbm/libpath.py
lightgbm/plotting.py
lightgbm/py.typed
lightgbm/sklearn.py
lightgbm-4.2.0.dist-info/METADATA
lightgbm-4.2.0.dist-info/WHEEL
lightgbm-4.2.0.dist-info/entry_points.txt
lightgbm-4.2.0.dist-info/licenses/LICENSE
lightgbm-4.2.0.dist-info/RECORD
