Metadata-Version: 2.1
Name: lightgbm
Version: 4.2.0
Summary: LightGBM Python Package
Home-page: https://github.com/microsoft/LightGBM
Maintainer-Email: Yu Shi <yushi@microsoft.com>
License: The MIT License (MIT)
Classifier: Development Status :: 5 - Production/Stable
Classifier: Intended Audience :: Science/Research
Classifier: License :: OSI Approved :: MIT License
Classifier: Natural Language :: English
Classifier: Operating System :: MacOS
Classifier: Operating System :: Microsoft :: Windows
Classifier: Operating System :: POSIX
Classifier: Operating System :: Unix
Classifier: Programming Language :: Python :: 3
Classifier: Programming Language :: Python :: 3.7
Classifier: Programming Language :: Python :: 3.8
Classifier: Programming Language :: Python :: 3.9
Classifier: Programming Language :: Python :: 3.10
Classifier: Programming Language :: Python :: 3.11
Classifier: Topic :: Scientific/Engineering :: Artificial Intelligence
Project-URL: Homepage, https://github.com/microsoft/LightGBM
Project-URL: Documentation, https://lightgbm.readthedocs.io/en/latest/
Project-URL: Repository, https://github.com/microsoft/LightGBM.git
Project-URL: Changelog, https://github.com/microsoft/LightGBM/releases
Requires-Python: >=3.6
Requires-Dist: dataclasses; python_version < "3.7"
Requires-Dist: numpy
Requires-Dist: scipy
Requires-Dist: cffi>=1.15.1; extra == "arrow"
Requires-Dist: pyarrow>=6.0.1; extra == "arrow"
Requires-Dist: dask[array,dataframe,distributed]>=2.0.0; extra == "dask"
Requires-Dist: pandas>=0.24.0; extra == "dask"
Requires-Dist: pandas>=0.24.0; extra == "pandas"
Requires-Dist: scikit-learn!=0.22.0; extra == "scikit-learn"
Provides-Extra: arrow
Provides-Extra: dask
Provides-Extra: pandas
Provides-Extra: scikit-learn
